kbow/__init__.py
kbow/core.py
kbow-0.1.0.dist-info/licenses/LICENSE
kbow-0.1.0.dist-info/METADATA
kbow-0.1.0.dist-info/WHEEL
kbow-0.1.0.dist-info/top_level.txt
kbow-0.1.0.dist-info/RECORD
