Metadata-Version: 2.4
Name: kbow
Version: 0.1.0
Summary: Minimal fuss Kmer bag of words model.
Author: pommevoid
License: MIT
Project-URL: Homepage, https://github.com/pommevoid/kbow
Requires-Python: >=3.8
License-File: LICENSE
Requires-Dist: numpy
Dynamic: license-file
